main.py
craft_scrapper_by-0.0.1.dist-info/licenses/LICENSE.txt
craft_scrapper_by-0.0.1.dist-info/METADATA
craft_scrapper_by-0.0.1.dist-info/WHEEL
craft_scrapper_by-0.0.1.dist-info/top_level.txt
craft_scrapper_by-0.0.1.dist-info/RECORD
