Metadata-Version: 2.4
Name: craft_scrapper_by
Version: 0.0.1
Summary: Minecraft recipe lib
Author-email: Al1ps <n4k7t9s228uk@gmail.com>
License: MIT License
Classifier: Programming Language :: Python :: 3
Classifier: Operating System :: OS Independent
Requires-Python: >=3.10
License-File: LICENSE.txt
Requires-Dist: requests>=2.32.3
Requires-Dist: beautifulsoup4>=4.13.3
Requires-Dist: pandas>=2.2.3
Dynamic: license-file
